README.md
setup.cfg
setup.py
mgsolver.egg-info/PKG-INFO
mgsolver.egg-info/SOURCES.txt
mgsolver.egg-info/dependency_links.txt
mgsolver.egg-info/top_level.txt
mgsolver/ball_sort_puzzle/__init__.py
mgsolver/ball_sort_puzzle/cells.py
mgsolver/ball_sort_puzzle/color.py
mgsolver/ball_sort_puzzle/solver.py
mgsolver/nonogram/__init__.py
mgsolver/nonogram/__main__.py
mgsolver/nonogram/data_resolver.py
mgsolver/nonogram/messages.py
mgsolver/nonogram/nonogram_marks.py
mgsolver/nonogram/size.py
mgsolver/nonogram/solver.py
mgsolver/nonogram/validators.py
mgsolver/sudoku/__init__.py
mgsolver/sudoku/solver.py
mgsolver/ball_sort_puzzle/__init__.py
mgsolver/ball_sort_puzzle/cells.py
mgsolver/ball_sort_puzzle/color.py
mgsolver/ball_sort_puzzle/solver.py
mgsolver/nonogram/__init__.py
mgsolver/nonogram/__main__.py
mgsolver/nonogram/data_resolver.py
mgsolver/nonogram/messages.py
mgsolver/nonogram/nonogram_marks.py
mgsolver/nonogram/size.py
mgsolver/nonogram/solver.py
mgsolver/nonogram/validators.py
mgsolver/sudoku/__init__.py
mgsolver/sudoku/solver.py
test/test_ball_sort_puzzle_solver.py
test/test_sudoku_solver.py