Metadata-Version: 1.1
Name: mgsolver
Version: 0.1.1
Summary: Collection of mini game solvers.
Home-page: https://github.com/romanstrazanec/mgsolver
Author: Roman Stražanec
Author-email: roman.strazanec007@gmail.com
License: MIT
Download-URL: https://github.com/romanstrazanec/mgsolver/releases/tag/v0.1.1
Keywords: mgsolver mini game solver
Platform: UNKNOWN
Classifier: Development Status :: 4 - Beta
Classifier: Environment :: Console
Classifier: Intended Audience :: Developers
Classifier: License :: OSI Approved :: MIT License
Classifier: Programming Language :: Python :: 3.8
Classifier: Topic :: Other/Nonlisted Topic
